memvectordb/__init__.py
memvectordb/collection.py
memvectordb/vectorstore.py
memvectordb_python-0.0.7.dist-info/METADATA
memvectordb_python-0.0.7.dist-info/WHEEL
memvectordb_python-0.0.7.dist-info/RECORD
