Metadata-Version: 2.1
Name: memvectordb-python
Version: 0.0.7
Summary: memvectordb python client.
Home-page: https://github.com/KevKibe/memvectordb-python-client
License: MIT
Author: Kevin Kibe
Author-email: keviinkibe@gmail.com
Classifier: License :: OSI Approved :: MIT License
Classifier: Programming Language :: Python :: 2
Classifier: Programming Language :: Python :: 2.7
Classifier: Programming Language :: Python :: 3
Classifier: Programming Language :: Python :: 3.4
Classifier: Programming Language :: Python :: 3.5
Classifier: Programming Language :: Python :: 3.6
Classifier: Programming Language :: Python :: 3.7
Classifier: Programming Language :: Python :: 3.8
Classifier: Programming Language :: Python :: 3.9
Classifier: Programming Language :: Python :: 3.10
Classifier: Programming Language :: Python :: 3.11
Classifier: Programming Language :: Python :: 3.12
Requires-Dist: langchain-text-splitters (==0.0.2)
Requires-Dist: langchain_community (==0.0.38)
Requires-Dist: openai (==1.30.5)
Requires-Dist: pypdf (==4.2.0)
Requires-Dist: python-dotenv (==1.0.1)
Requires-Dist: requests (==2.31.0)
Requires-Dist: sentence_transformers (==3.0.1)
Project-URL: Repository, https://github.com/KevKibe/memvectordb-python-client
